Metadata-Version: 1.0
Name: debrepo
Version: 0.0.3
Summary: Inspect and compare Debian repositories
Home-page: https://pagure.io/debrepo
Author: Andrew Hills
Author-email: ahills@redhat.com
License: GPL
Keywords: compose,repodiff
Platform: UNKNOWN
